spherediff/__init__.py
spherediff/coeffs.py
spherediff/kernel.py
spherediff/poly.py
spherediff/sample.py
spherediff/score.py
spherediff-1.2.2.dist-info/LICENSE.txt
spherediff-1.2.2.dist-info/METADATA
spherediff-1.2.2.dist-info/WHEEL
spherediff-1.2.2.dist-info/top_level.txt
spherediff-1.2.2.dist-info/RECORD
