Metadata-Version: 2.1
Name: spherediff
Version: 1.2.2
Summary: Sample from the diffusion kernel on any n-sphere
Author-email: Rian Kormos <Rian.Kormos@ucsf.edu>
Project-URL: Homepage, https://github.com/rckormos/SphereDiff
Keywords: diffusion,hypersphere,sampling
Classifier: License :: OSI Approved :: MIT License
Classifier: Programming Language :: Python
Classifier: Programming Language :: Python :: 3
Requires-Python: >=3.8
License-File: LICENSE.txt
Requires-Dist: numpy (>=1.18.0)
Requires-Dist: numba (>=0.47.0)
Requires-Dist: scipy (>=1.4.0)
Requires-Dist: tomli ; python_version < "3.11"
